_cuTWED.abi3.so
_cuTWED_build.py
cuTWED.py
_CTWED.abi3.so
__init__.py
CTWED.py
_CTWED_build.py
cuTWED.libs/libcuTWED-9ac2ed36.so
cuTWED.libs/libcublas-77ef0e44.so.10.2.1.243
cuTWED.libs/libcublasLt-5b603012.so.10.2.1.243
cuTWED-2.0.2.dist-info/top_level.txt
cuTWED-2.0.2.dist-info/WHEEL
cuTWED-2.0.2.dist-info/AUTHORS.rst
cuTWED-2.0.2.dist-info/RECORD
cuTWED-2.0.2.dist-info/LICENSE
cuTWED-2.0.2.dist-info/METADATA
cuTWED-2.0.2.data/headers/cuTWED.h.i
cuTWED-2.0.2.data/headers/twed.h
