Metadata-Version: 2.1
Name: cuTWED
Version: 2.0.2
Summary: A linear memory CUDA Time Warp Edit Distance algorithm.
Home-page: https://github.com/garrettwrong/cuTWED
Author: Garrett Wright
Author-email: garrett@gestaltgp.com
License: UNKNOWN
Project-URL: Issue Tracker, https://github.com/garrettwrong/cuTWED/issues
Platform: UNKNOWN
Classifier: Development Status :: 4 - Beta
Classifier: Intended Audience :: Science/Research
Classifier: Topic :: Scientific/Engineering :: Mathematics
Classifier: Topic :: Scientific/Engineering :: Artificial Intelligence
Classifier: Programming Language :: C
Classifier: Programming Language :: Python
Classifier: Programming Language :: Python :: 3.7
Classifier: Programming Language :: Python :: Implementation :: CPython
Classifier: License :: OSI Approved :: GNU General Public License v3 or later (GPLv3+)
Requires-Python: !=3.0.*, !=3.1.*, !=3.2.*, !=3.3.*, !=3.4.*
Provides-Extra: dev
